djatex/__init__.py
djatex/latex_file.py
djatex/render.py
djatex/version.py
djatex-0.1.16.dist-info/LICENSE.txt
djatex-0.1.16.dist-info/METADATA
djatex-0.1.16.dist-info/WHEEL
djatex-0.1.16.dist-info/top_level.txt
djatex-0.1.16.dist-info/RECORD
