Metadata-Version: 2.1
Name: djatex
Version: 0.1.16
Summary: Generate pdf from latex in django
Home-page: https://bitbucket.org/marc_culler/djatex
Author: Marc Culler
Author-email: mcbugs000@gmail.com
License: GPL
Keywords: django latex pdf
Platform: UNKNOWN
Classifier: Development Status :: 4 - Beta
Classifier: Intended Audience :: Developers
Classifier: Topic :: Software Development
Classifier: Framework :: Django
Classifier: License :: OSI Approved :: GNU General Public License v2 or later (GPLv2+)
Classifier: Programming Language :: Python :: 3.5
Classifier: Programming Language :: Python :: 3.6
Requires-Dist: django
